{
  "project": {
    "id": "sample_organize_275",
    "name": "デジタル整理",
    "description": "散らかった物を効率的に整理整頓する。",
    "createdAt": "2025-11-14T00:00:00.000Z",
    "lastModified": "2025-11-14T00:00:00.000Z",
    "version": "1.0.0",
    "creator": {"userId": "sample_creator", "username": "Sample Games", "isAnonymous": false},
    "assets": {
      "background": {"id": "bg_275", "name": "背景", "type": "background", "frames": [{"id": "fbg", "frameNumber": 0, "dataUrl": "data:image/svg+xml,%3Csvg xmlns='http://www.w3.org/2000/svg' width='360' height='640'%3E%3Crect width='360' height='640' fill='%23BCAAA4'/%3E%3C/svg%3E", "width": 360, "height": 640, "fileSize": 300}], "defaultScale": 1, "totalSize": 300, "createdAt": "2025-11-14T00:00:00.000Z"},
      "objects": [
        {"id": "obj1", "name": "物1", "type": "object", "frames": [{"id": "o1", "frameNumber": 0, "dataUrl": "data:image/svg+xml,%3Csvg xmlns='http://www.w3.org/2000/svg' width='50' height='50'%3E%3Crect x='10' y='10' width='30' height='30' fill='%234CAF50'/%3E%3C/svg%3E", "width": 50, "height": 50, "fileSize": 300}], "defaultScale": 1, "totalSize": 300, "createdAt": "2025-11-14T00:00:00.000Z"},
        {"id": "obj2", "name": "物2", "type": "object", "frames": [{"id": "o2", "frameNumber": 0, "dataUrl": "data:image/svg+xml,%3Csvg xmlns='http://www.w3.org/2000/svg' width='50' height='50'%3E%3Ccircle cx='25' cy='25' r='20' fill='%232196F3'/%3E%3C/svg%3E", "width": 50, "height": 50, "fileSize": 300}], "defaultScale": 1, "totalSize": 300, "createdAt": "2025-11-14T00:00:00.000Z"},
        {"id": "obj3", "name": "物3", "type": "object", "frames": [{"id": "o3", "frameNumber": 0, "dataUrl": "data:image/svg+xml,%3Csvg xmlns='http://www.w3.org/2000/svg' width='50' height='50'%3E%3Cpolygon points='25,5 45,40 5,40' fill='%23FF9800'/%3E%3C/svg%3E", "width": 50, "height": 50, "fileSize": 300}], "defaultScale": 1, "totalSize": 300, "createdAt": "2025-11-14T00:00:00.000Z"}
      ]
    },
    "layout": {
      "background": {"assetId": "bg_275", "position": {"x": 0, "y": 0}, "scale": 1, "rotation": 0, "zIndex": 0},
      "objects": [
        {"assetId": "obj1", "position": {"x": 70, "y": 280}, "scale": 1, "rotation": 15, "zIndex": 1},
        {"assetId": "obj2", "position": {"x": 155, "y": 300}, "scale": 1, "rotation": -20, "zIndex": 1},
        {"assetId": "obj3", "position": {"x": 240, "y": 270}, "scale": 1, "rotation": 30, "zIndex": 1}
      ]
    },
    "script": {
      "rules": [
        {"id": "rule_o1", "name": "物1整理", "enabled": true, "targetObjectId": "obj1", "triggers": {"conditions": [{"type": "touch", "target": "self"}]}, "actions": [{"type": "hide", "target": "self"}, {"type": "addScore", "value": 100}]},
        {"id": "rule_o2", "name": "物2整理", "enabled": true, "targetObjectId": "obj2", "triggers": {"conditions": [{"type": "touch", "target": "self"}]}, "actions": [{"type": "hide", "target": "self"}, {"type": "addScore", "value": 100}]},
        {"id": "rule_o3", "name": "物3整理", "enabled": true, "targetObjectId": "obj3", "triggers": {"conditions": [{"type": "touch", "target": "self"}]}, "actions": [{"type": "hide", "target": "self"}, {"type": "success", "score": 1000}]}
      ],
      "variables": [],
      "initialVariables": {}
    },
    "settings": {"gameDuration": 20, "difficulty": "easy", "genre": "puzzle", "tags": ["整理", "掃除", "YouTube"], "allowCopying": true, "isPublic": true}
  },
  "metadata": {"id": "sample_organize_275", "name": "デジタル整理", "lastModified": "2025-11-14T00:00:00.000Z", "status": "published", "size": 1850, "version": "1.0.0"},
  "exportedAt": "2025-11-14T00:00:00.000Z",
  "version": "1.0.0"
}
